edgeidx/__init__.py
edgeidx/ocr.py
edgeidx/utils.py
edgeidx/tesseract/libgcc_s_seh-1.dll
edgeidx/tesseract/libleptonica-6.dll
edgeidx/tesseract/libstdc++-6.dll
edgeidx/tesseract/libtesseract-5.dll
edgeidx/tesseract/libwinpthread-1.dll
edgeidx/tesseract/tesseract.exe
edgeidx/tesseract/zlib1.dll
edgeidx/tesseract/Tesseract-OCR/ambiguous_words.1.html
edgeidx/tesseract/Tesseract-OCR/ambiguous_words.exe
edgeidx/tesseract/Tesseract-OCR/classifier_tester.1.html
edgeidx/tesseract/Tesseract-OCR/classifier_tester.exe
edgeidx/tesseract/Tesseract-OCR/cntraining.1.html
edgeidx/tesseract/Tesseract-OCR/cntraining.exe
edgeidx/tesseract/Tesseract-OCR/combine_lang_model.1.html
edgeidx/tesseract/Tesseract-OCR/combine_lang_model.exe
edgeidx/tesseract/Tesseract-OCR/combine_tessdata.1.html
edgeidx/tesseract/Tesseract-OCR/combine_tessdata.exe
edgeidx/tesseract/Tesseract-OCR/dawg2wordlist.1.html
edgeidx/tesseract/Tesseract-OCR/dawg2wordlist.exe
edgeidx/tesseract/Tesseract-OCR/libLerc.dll
edgeidx/tesseract/Tesseract-OCR/libarchive-13.dll
edgeidx/tesseract/Tesseract-OCR/libb2-1.dll
edgeidx/tesseract/Tesseract-OCR/libbrotlicommon.dll
edgeidx/tesseract/Tesseract-OCR/libbrotlidec.dll
edgeidx/tesseract/Tesseract-OCR/libbz2-1.dll
edgeidx/tesseract/Tesseract-OCR/libcairo-2.dll
edgeidx/tesseract/Tesseract-OCR/libcrypto-3-x64.dll
edgeidx/tesseract/Tesseract-OCR/libcurl-4.dll
edgeidx/tesseract/Tesseract-OCR/libdatrie-1.dll
edgeidx/tesseract/Tesseract-OCR/libdeflate.dll
edgeidx/tesseract/Tesseract-OCR/libexpat-1.dll
edgeidx/tesseract/Tesseract-OCR/libffi-8.dll
edgeidx/tesseract/Tesseract-OCR/libfontconfig-1.dll
edgeidx/tesseract/Tesseract-OCR/libfreetype-6.dll
edgeidx/tesseract/Tesseract-OCR/libfribidi-0.dll
edgeidx/tesseract/Tesseract-OCR/libgcc_s_seh-1.dll
edgeidx/tesseract/Tesseract-OCR/libgif-7.dll
edgeidx/tesseract/Tesseract-OCR/libgio-2.0-0.dll
edgeidx/tesseract/Tesseract-OCR/libglib-2.0-0.dll
edgeidx/tesseract/Tesseract-OCR/libgmodule-2.0-0.dll
edgeidx-3.0.0.dist-info/METADATA
edgeidx-3.0.0.dist-info/WHEEL
edgeidx-3.0.0.dist-info/top_level.txt
edgeidx-3.0.0.dist-info/RECORD
