Metadata-Version: 2.4
Name: edgeidx
Version: 3.0.0
Summary: EdgeIDX is a Windows-only Python library for OCR that extracts information from Aadhaar and PAN cards with embedded Tesseract engine.
Author: Nawaz Sayyad, Kunal Chandak, Mayuresh Muluk, Harshal Pathare
Author-email: kmcwankhed2021@gmail.com
Project-URL: Source, https://github.com/yourusername/edgeidx
Project-URL: Bug Reports, https://github.com/yourusername/edgeidx/issues
Keywords: ocr aadhaar pan-card windows document-extraction
Classifier: Programming Language :: Python :: 3
Classifier: License :: OSI Approved :: MIT License
Classifier: Operating System :: Microsoft :: Windows
Classifier: Development Status :: 4 - Beta
Classifier: Intended Audience :: Developers
Classifier: Topic :: Software Development :: Libraries :: Python Modules
Classifier: Topic :: Text Processing
Requires-Python: >=3.6
Requires-Dist: pytesseract>=0.3.10
Requires-Dist: opencv-python>=4.5.0
Requires-Dist: numpy>=1.21.0
Requires-Dist: Pillow>=9.0.0
Dynamic: author
Dynamic: author-email
Dynamic: classifier
Dynamic: description
Dynamic: description-content-type
Dynamic: keywords
Dynamic: project-url
Dynamic: requires-dist
Dynamic: requires-python
Dynamic: summary
